ngxgen_app/__init__.py
ngxgen_app/App/AppRunner.py
ngxgen_app/App/Program.py
ngxgen_app/App/__init__.py
ngxgen_app/Builder/CliBuilder.py
ngxgen_app/Builder/__init__.py
ngxgen_app/Entities/NginxConfig.py
ngxgen_app-1.0.2.dist-info/entry_points.txt
ngxgen_app-1.0.2.dist-info/WHEEL
ngxgen_app-1.0.2.dist-info/METADATA
ngxgen_app-1.0.2.dist-info/RECORD
