Metadata-Version: 2.4
Name: ngxgen-app
Version: 1.0.2
Summary: NgxGen - generate Nginx configuration from YAML files.
Author-email: Maciej Barć <xgqt@xgqt.org>
Requires-Python: >=3.13
Classifier: Environment :: Console
Classifier: Operating System :: POSIX
Classifier: Programming Language :: Python :: 3 :: Only
Requires-Dist: pyyaml>=6.0.3
